[
  {
    "line": 2,
    "elements": [
      {
        "start_timestamp": "2021-10-12T09:16:21.388Z",
        "before": [
          {
            "result": {
              "duration": 1409650500,
              "status": "passed"
            },
            "match": {
              "location": "com.qa.stepDefs.Hook.setUp()"
            }
          }
        ],
        "line": 5,
        "name": "user is able to see Services",
        "description": "",
        "id": "best-buy-services;user-is-able-to-see-services",
        "type": "scenario",
        "keyword": "Scenario",
        "steps": [
          {
            "result": {
              "error_message": "java.net.ConnectException: Connection refused: connect\r\n\tat java.base/sun.nio.ch.Net.connect0(Native Method)\r\n\tat java.base/sun.nio.ch.Net.connect(Net.java:503)\r\n\tat java.base/sun.nio.ch.Net.connect(Net.java:492)\r\n\tat java.base/sun.nio.ch.NioSocketImpl.connect(NioSocketImpl.java:588)\r\n\tat java.base/java.net.SocksSocketImpl.connect(SocksSocketImpl.java:333)\r\n\tat java.base/java.net.Socket.connect(Socket.java:648)\r\n\tat org.apache.http.conn.scheme.PlainSocketFactory.connectSocket(PlainSocketFactory.java:121)\r\n\tat org.apache.http.impl.conn.DefaultClientConnectionOperator.openConnection(DefaultClientConnectionOperator.java:180)\r\n\tat org.apache.http.impl.conn.ManagedClientConnectionImpl.open(ManagedClientConnectionImpl.java:326)\r\n\tat org.apache.http.impl.client.DefaultRequestDirector.tryConnect(DefaultRequestDirector.java:610)\r\n\tat org.apache.http.impl.client.DefaultRequestDirector.execute(DefaultRequestDirector.java:445)\r\n\tat org.apache.http.impl.client.AbstractHttpClient.doExecute(AbstractHttpClient.java:835)\r\n\tat org.apache.http.impl.client.CloseableHttpClient.execute(CloseableHttpClient.java:83)\r\n\tat org.apache.http.impl.client.CloseableHttpClient.execute(CloseableHttpClient.java:56)\r\n\tat org.apache.http.client.HttpClient$execute$0.call(Unknown Source)\r\n\tat org.codehaus.groovy.runtime.callsite.CallSiteArray.defaultCall(CallSiteArray.java:47)\r\n\tat org.codehaus.groovy.runtime.callsite.AbstractCallSite.call(AbstractCallSite.java:125)\r\n\tat org.codehaus.groovy.runtime.callsite.AbstractCallSite.call(AbstractCallSite.java:148)\r\n\tat io.restassured.internal.RequestSpecificationImpl$RestAssuredHttpBuilder.doRequest(RequestSpecificationImpl.groovy:2055)\r\n\tat io.restassured.internal.http.HTTPBuilder.doRequest(HTTPBuilder.java:495)\r\n\tat io.restassured.internal.http.HTTPBuilder.request(HTTPBuilder.java:452)\r\n\tat io.restassured.internal.http.HTTPBuilder$request$2.call(Unknown Source)\r\n\tat org.codehaus.groovy.runtime.callsite.CallSiteArray.defaultCall(CallSiteArray.java:47)\r\n\tat org.codehaus.groovy.runtime.callsite.AbstractCallSite.call(AbstractCallSite.java:125)\r\n\tat org.codehaus.groovy.runtime.callsite.AbstractCallSite.call(AbstractCallSite.java:166)\r\n\tat io.restassured.internal.RequestSpecificationImpl.sendHttpRequest(RequestSpecificationImpl.groovy:1451)\r\n\tat java.base/jdk.internal.reflect.NativeMethodAccessorImpl.invoke0(Native Method)\r\n\tat java.base/jdk.internal.reflect.NativeMethodAccessorImpl.invoke(NativeMethodAccessorImpl.java:62)\r\n\tat java.base/jdk.internal.reflect.DelegatingMethodAccessorImpl.invoke(DelegatingMethodAccessorImpl.java:43)\r\n\tat java.base/java.lang.reflect.Method.invoke(Method.java:564)\r\n\tat org.codehaus.groovy.reflection.CachedMethod.invoke(CachedMethod.java:107)\r\n\tat groovy.lang.MetaMethod.doMethodInvoke(MetaMethod.java:323)\r\n\tat groovy.lang.MetaClassImpl.invokeMethod(MetaClassImpl.java:1267)\r\n\tat groovy.lang.MetaClassImpl.invokeMethod(MetaClassImpl.java:1034)\r\n\tat groovy.lang.MetaClassImpl.invokeMethod(MetaClassImpl.java:818)\r\n\tat groovy.lang.GroovyObject.invokeMethod(GroovyObject.java:39)\r\n\tat org.codehaus.groovy.runtime.callsite.PogoInterceptableSite.call(PogoInterceptableSite.java:45)\r\n\tat org.codehaus.groovy.runtime.callsite.PogoInterceptableSite.callCurrent(PogoInterceptableSite.java:55)\r\n\tat org.codehaus.groovy.runtime.callsite.CallSiteArray.defaultCallCurrent(CallSiteArray.java:51)\r\n\tat org.codehaus.groovy.runtime.callsite.AbstractCallSite.callCurrent(AbstractCallSite.java:171)\r\n\tat io.restassured.internal.RequestSpecificationImpl.sendRequest(RequestSpecificationImpl.groovy:1200)\r\n\tat java.base/jdk.internal.reflect.NativeMethodAccessorImpl.invoke0(Native Method)\r\n\tat java.base/jdk.internal.reflect.NativeMethodAccessorImpl.invoke(NativeMethodAccessorImpl.java:62)\r\n\tat java.base/jdk.internal.reflect.DelegatingMethodAccessorImpl.invoke(DelegatingMethodAccessorImpl.java:43)\r\n\tat java.base/java.lang.reflect.Method.invoke(Method.java:564)\r\n\tat org.codehaus.groovy.reflection.CachedMethod.invoke(CachedMethod.java:107)\r\n\tat groovy.lang.MetaMethod.doMethodInvoke(MetaMethod.java:323)\r\n\tat groovy.lang.MetaClassImpl.invokeMethod(MetaClassImpl.java:1267)\r\n\tat groovy.lang.MetaClassImpl.invokeMethod(MetaClassImpl.java:1034)\r\n\tat groovy.lang.MetaClassImpl.invokeMethod(MetaClassImpl.java:818)\r\n\tat groovy.lang.GroovyObject.invokeMethod(GroovyObject.java:39)\r\n\tat org.codehaus.groovy.runtime.callsite.PogoInterceptableSite.call(PogoInterceptableSite.java:45)\r\n\tat org.codehaus.groovy.runtime.callsite.CallSiteArray.defaultCall(CallSiteArray.java:47)\r\n\tat org.codehaus.groovy.runtime.callsite.AbstractCallSite.call(AbstractCallSite.java:125)\r\n\tat org.codehaus.groovy.runtime.callsite.AbstractCallSite.call(AbstractCallSite.java:166)\r\n\tat io.restassured.internal.filter.SendRequestFilter.filter(SendRequestFilter.groovy:30)\r\n\tat io.restassured.filter.Filter$filter$0.call(Unknown Source)\r\n\tat org.codehaus.groovy.runtime.callsite.CallSiteArray.defaultCall(CallSiteArray.java:47)\r\n\tat io.restassured.filter.Filter$filter.call(Unknown Source)\r\n\tat io.restassured.internal.filter.FilterContextImpl.next(FilterContextImpl.groovy:72)\r\n\tat io.restassured.filter.time.TimingFilter.filter(TimingFilter.java:56)\r\n\tat io.restassured.filter.Filter$filter.call(Unknown Source)\r\n\tat org.codehaus.groovy.runtime.callsite.CallSiteArray.defaultCall(CallSiteArray.java:47)\r\n\tat org.codehaus.groovy.runtime.callsite.AbstractCallSite.call(AbstractCallSite.java:125)\r\n\tat org.codehaus.groovy.runtime.callsite.AbstractCallSite.call(AbstractCallSite.java:157)\r\n\tat io.restassured.internal.filter.FilterContextImpl.next(FilterContextImpl.groovy:72)\r\n\tat io.restassured.filter.FilterContext$next.call(Unknown Source)\r\n\tat org.codehaus.groovy.runtime.callsite.CallSiteArray.defaultCall(CallSiteArray.java:47)\r\n\tat org.codehaus.groovy.runtime.callsite.AbstractCallSite.call(AbstractCallSite.java:125)\r\n\tat org.codehaus.groovy.runtime.callsite.AbstractCallSite.call(AbstractCallSite.java:148)\r\n\tat io.restassured.internal.RequestSpecificationImpl.applyPathParamsAndSendRequest(RequestSpecificationImpl.groovy:1655)\r\n\tat java.base/jdk.internal.reflect.NativeMethodAccessorImpl.invoke0(Native Method)\r\n\tat java.base/jdk.internal.reflect.NativeMethodAccessorImpl.invoke(NativeMethodAccessorImpl.java:62)\r\n\tat java.base/jdk.internal.reflect.DelegatingMethodAccessorImpl.invoke(DelegatingMethodAccessorImpl.java:43)\r\n\tat java.base/java.lang.reflect.Method.invoke(Method.java:564)\r\n\tat org.codehaus.groovy.reflection.CachedMethod.invoke(CachedMethod.java:107)\r\n\tat groovy.lang.MetaMethod.doMethodInvoke(MetaMethod.java:323)\r\n\tat groovy.lang.MetaClassImpl.invokeMethod(MetaClassImpl.java:1267)\r\n\tat groovy.lang.MetaClassImpl.invokeMethod(MetaClassImpl.java:1034)\r\n\tat groovy.lang.MetaClassImpl.invokeMethod(MetaClassImpl.java:818)\r\n\tat groovy.lang.GroovyObject.invokeMethod(GroovyObject.java:39)\r\n\tat org.codehaus.groovy.runtime.callsite.PogoInterceptableSite.call(PogoInterceptableSite.java:45)\r\n\tat org.codehaus.groovy.runtime.callsite.PogoInterceptableSite.callCurrent(PogoInterceptableSite.java:55)\r\n\tat org.codehaus.groovy.runtime.callsite.CallSiteArray.defaultCallCurrent(CallSiteArray.java:51)\r\n\tat org.codehaus.groovy.runtime.callsite.AbstractCallSite.callCurrent(AbstractCallSite.java:171)\r\n\tat org.codehaus.groovy.runtime.callsite.AbstractCallSite.callCurrent(AbstractCallSite.java:203)\r\n\tat io.restassured.internal.RequestSpecificationImpl.applyPathParamsAndSendRequest(RequestSpecificationImpl.groovy:1661)\r\n\tat java.base/jdk.internal.reflect.NativeMethodAccessorImpl.invoke0(Native Method)\r\n\tat java.base/jdk.internal.reflect.NativeMethodAccessorImpl.invoke(NativeMethodAccessorImpl.java:62)\r\n\tat java.base/jdk.internal.reflect.DelegatingMethodAccessorImpl.invoke(DelegatingMethodAccessorImpl.java:43)\r\n\tat java.base/java.lang.reflect.Method.invoke(Method.java:564)\r\n\tat org.codehaus.groovy.reflection.CachedMethod.invoke(CachedMethod.java:107)\r\n\tat groovy.lang.MetaMethod.doMethodInvoke(MetaMethod.java:323)\r\n\tat groovy.lang.MetaClassImpl.invokeMethod(MetaClassImpl.java:1267)\r\n\tat groovy.lang.MetaClassImpl.invokeMethod(MetaClassImpl.java:1034)\r\n\tat groovy.lang.MetaClassImpl.invokeMethod(MetaClassImpl.java:818)\r\n\tat groovy.lang.GroovyObject.invokeMethod(GroovyObject.java:39)\r\n\tat org.codehaus.groovy.runtime.callsite.PogoInterceptableSite.call(PogoInterceptableSite.java:45)\r\n\tat org.codehaus.groovy.runtime.callsite.PogoInterceptableSite.callCurrent(PogoInterceptableSite.java:55)\r\n\tat org.codehaus.groovy.runtime.callsite.CallSiteArray.defaultCallCurrent(CallSiteArray.java:51)\r\n\tat org.codehaus.groovy.runtime.callsite.AbstractCallSite.callCurrent(AbstractCallSite.java:171)\r\n\tat org.codehaus.groovy.runtime.callsite.AbstractCallSite.callCurrent(AbstractCallSite.java:203)\r\n\tat io.restassured.internal.RequestSpecificationImpl.get(RequestSpecificationImpl.groovy:171)\r\n\tat io.restassured.internal.RequestSpecificationImpl.get(RequestSpecificationImpl.groovy)\r\n\tat com.qa.stepDefs.ServicesStepDef.user_sends_a_GET_request_to_see_services(ServicesStepDef.java:25)\r\n\tat ✽.user sends a GET request to see services(file:///C:/Users/Naim/Desktop/IT/Projeler%20IntelliJ/bestBuyApi1/src/test/resources/features/services.feature:6)\r\n",
              "duration": 6543200800,
              "status": "failed"
            },
            "line": 6,
            "name": "user sends a GET request to see services",
            "match": {
              "location": "com.qa.stepDefs.ServicesStepDef.user_sends_a_GET_request_to_see_services()"
            },
            "keyword": "When "
          }
        ],
        "tags": [
          {
            "name": "@service"
          },
          {
            "name": "@smoke"
          }
        ]
      },
      {
        "start_timestamp": "2021-10-12T09:16:29.762Z",
        "before": [
          {
            "result": {
              "status": "passed"
            },
            "match": {
              "location": "com.qa.stepDefs.Hook.setUp()"
            }
          }
        ],
        "line": 8,
        "name": "user able to skip services",
        "description": "",
        "id": "best-buy-services;user-able-to-skip-services",
        "type": "scenario",
        "keyword": "Scenario",
        "steps": [
          {
            "result": {
              "error_message": "java.net.ConnectException: Connection refused: connect\r\n\tat java.base/sun.nio.ch.Net.connect0(Native Method)\r\n\tat java.base/sun.nio.ch.Net.connect(Net.java:503)\r\n\tat java.base/sun.nio.ch.Net.connect(Net.java:492)\r\n\tat java.base/sun.nio.ch.NioSocketImpl.connect(NioSocketImpl.java:588)\r\n\tat java.base/java.net.SocksSocketImpl.connect(SocksSocketImpl.java:333)\r\n\tat java.base/java.net.Socket.connect(Socket.java:648)\r\n\tat org.apache.http.conn.scheme.PlainSocketFactory.connectSocket(PlainSocketFactory.java:121)\r\n\tat org.apache.http.impl.conn.DefaultClientConnectionOperator.openConnection(DefaultClientConnectionOperator.java:180)\r\n\tat org.apache.http.impl.conn.ManagedClientConnectionImpl.open(ManagedClientConnectionImpl.java:326)\r\n\tat org.apache.http.impl.client.DefaultRequestDirector.tryConnect(DefaultRequestDirector.java:610)\r\n\tat org.apache.http.impl.client.DefaultRequestDirector.execute(DefaultRequestDirector.java:445)\r\n\tat org.apache.http.impl.client.AbstractHttpClient.doExecute(AbstractHttpClient.java:835)\r\n\tat org.apache.http.impl.client.CloseableHttpClient.execute(CloseableHttpClient.java:83)\r\n\tat org.apache.http.impl.client.CloseableHttpClient.execute(CloseableHttpClient.java:56)\r\n\tat org.apache.http.client.HttpClient$execute$0.call(Unknown Source)\r\n\tat io.restassured.internal.RequestSpecificationImpl$RestAssuredHttpBuilder.doRequest(RequestSpecificationImpl.groovy:2055)\r\n\tat io.restassured.internal.http.HTTPBuilder.doRequest(HTTPBuilder.java:495)\r\n\tat io.restassured.internal.http.HTTPBuilder.request(HTTPBuilder.java:452)\r\n\tat io.restassured.internal.http.HTTPBuilder$request$2.call(Unknown Source)\r\n\tat io.restassured.internal.RequestSpecificationImpl.sendHttpRequest(RequestSpecificationImpl.groovy:1451)\r\n\tat java.base/jdk.internal.reflect.NativeMethodAccessorImpl.invoke0(Native Method)\r\n\tat java.base/jdk.internal.reflect.NativeMethodAccessorImpl.invoke(NativeMethodAccessorImpl.java:62)\r\n\tat java.base/jdk.internal.reflect.DelegatingMethodAccessorImpl.invoke(DelegatingMethodAccessorImpl.java:43)\r\n\tat java.base/java.lang.reflect.Method.invoke(Method.java:564)\r\n\tat org.codehaus.groovy.reflection.CachedMethod.invoke(CachedMethod.java:107)\r\n\tat groovy.lang.MetaMethod.doMethodInvoke(MetaMethod.java:323)\r\n\tat groovy.lang.MetaClassImpl.invokeMethod(MetaClassImpl.java:1267)\r\n\tat groovy.lang.MetaClassImpl.invokeMethod(MetaClassImpl.java:1034)\r\n\tat groovy.lang.MetaClassImpl.invokeMethod(MetaClassImpl.java:818)\r\n\tat groovy.lang.GroovyObject.invokeMethod(GroovyObject.java:39)\r\n\tat org.codehaus.groovy.runtime.callsite.PogoInterceptableSite.call(PogoInterceptableSite.java:45)\r\n\tat org.codehaus.groovy.runtime.callsite.PogoInterceptableSite.callCurrent(PogoInterceptableSite.java:55)\r\n\tat io.restassured.internal.RequestSpecificationImpl.sendRequest(RequestSpecificationImpl.groovy:1200)\r\n\tat java.base/jdk.internal.reflect.NativeMethodAccessorImpl.invoke0(Native Method)\r\n\tat java.base/jdk.internal.reflect.NativeMethodAccessorImpl.invoke(NativeMethodAccessorImpl.java:62)\r\n\tat java.base/jdk.internal.reflect.DelegatingMethodAccessorImpl.invoke(DelegatingMethodAccessorImpl.java:43)\r\n\tat java.base/java.lang.reflect.Method.invoke(Method.java:564)\r\n\tat org.codehaus.groovy.reflection.CachedMethod.invoke(CachedMethod.java:107)\r\n\tat groovy.lang.MetaMethod.doMethodInvoke(MetaMethod.java:323)\r\n\tat groovy.lang.MetaClassImpl.invokeMethod(MetaClassImpl.java:1267)\r\n\tat groovy.lang.MetaClassImpl.invokeMethod(MetaClassImpl.java:1034)\r\n\tat groovy.lang.MetaClassImpl.invokeMethod(MetaClassImpl.java:818)\r\n\tat groovy.lang.GroovyObject.invokeMethod(GroovyObject.java:39)\r\n\tat org.codehaus.groovy.runtime.callsite.PogoInterceptableSite.call(PogoInterceptableSite.java:45)\r\n\tat org.codehaus.groovy.runtime.callsite.AbstractCallSite.call(AbstractCallSite.java:166)\r\n\tat io.restassured.internal.filter.SendRequestFilter.filter(SendRequestFilter.groovy:30)\r\n\tat io.restassured.filter.Filter$filter$0.call(Unknown Source)\r\n\tat org.codehaus.groovy.runtime.callsite.CallSiteArray.defaultCall(CallSiteArray.java:47)\r\n\tat io.restassured.filter.Filter$filter.call(Unknown Source)\r\n\tat io.restassured.internal.filter.FilterContextImpl.next(FilterContextImpl.groovy:72)\r\n\tat io.restassured.filter.time.TimingFilter.filter(TimingFilter.java:56)\r\n\tat io.restassured.filter.Filter$filter.call(Unknown Source)\r\n\tat org.codehaus.groovy.runtime.callsite.CallSiteArray.defaultCall(CallSiteArray.java:47)\r\n\tat io.restassured.filter.Filter$filter$0.call(Unknown Source)\r\n\tat io.restassured.internal.filter.FilterContextImpl.next(FilterContextImpl.groovy:72)\r\n\tat io.restassured.filter.FilterContext$next.call(Unknown Source)\r\n\tat io.restassured.internal.RequestSpecificationImpl.applyPathParamsAndSendRequest(RequestSpecificationImpl.groovy:1655)\r\n\tat java.base/jdk.internal.reflect.NativeMethodAccessorImpl.invoke0(Native Method)\r\n\tat java.base/jdk.internal.reflect.NativeMethodAccessorImpl.invoke(NativeMethodAccessorImpl.java:62)\r\n\tat java.base/jdk.internal.reflect.DelegatingMethodAccessorImpl.invoke(DelegatingMethodAccessorImpl.java:43)\r\n\tat java.base/java.lang.reflect.Method.invoke(Method.java:564)\r\n\tat org.codehaus.groovy.reflection.CachedMethod.invoke(CachedMethod.java:107)\r\n\tat groovy.lang.MetaMethod.doMethodInvoke(MetaMethod.java:323)\r\n\tat groovy.lang.MetaClassImpl.invokeMethod(MetaClassImpl.java:1267)\r\n\tat groovy.lang.MetaClassImpl.invokeMethod(MetaClassImpl.java:1034)\r\n\tat groovy.lang.MetaClassImpl.invokeMethod(MetaClassImpl.java:818)\r\n\tat groovy.lang.GroovyObject.invokeMethod(GroovyObject.java:39)\r\n\tat org.codehaus.groovy.runtime.callsite.PogoInterceptableSite.call(PogoInterceptableSite.java:45)\r\n\tat org.codehaus.groovy.runtime.callsite.PogoInterceptableSite.callCurrent(PogoInterceptableSite.java:55)\r\n\tat org.codehaus.groovy.runtime.callsite.AbstractCallSite.callCurrent(AbstractCallSite.java:203)\r\n\tat io.restassured.internal.RequestSpecificationImpl.applyPathParamsAndSendRequest(RequestSpecificationImpl.groovy:1661)\r\n\tat java.base/jdk.internal.reflect.NativeMethodAccessorImpl.invoke0(Native Method)\r\n\tat java.base/jdk.internal.reflect.NativeMethodAccessorImpl.invoke(NativeMethodAccessorImpl.java:62)\r\n\tat java.base/jdk.internal.reflect.DelegatingMethodAccessorImpl.invoke(DelegatingMethodAccessorImpl.java:43)\r\n\tat java.base/java.lang.reflect.Method.invoke(Method.java:564)\r\n\tat org.codehaus.groovy.reflection.CachedMethod.invoke(CachedMethod.java:107)\r\n\tat groovy.lang.MetaMethod.doMethodInvoke(MetaMethod.java:323)\r\n\tat groovy.lang.MetaClassImpl.invokeMethod(MetaClassImpl.java:1267)\r\n\tat groovy.lang.MetaClassImpl.invokeMethod(MetaClassImpl.java:1034)\r\n\tat groovy.lang.MetaClassImpl.invokeMethod(MetaClassImpl.java:818)\r\n\tat groovy.lang.GroovyObject.invokeMethod(GroovyObject.java:39)\r\n\tat org.codehaus.groovy.runtime.callsite.PogoInterceptableSite.call(PogoInterceptableSite.java:45)\r\n\tat org.codehaus.groovy.runtime.callsite.PogoInterceptableSite.callCurrent(PogoInterceptableSite.java:55)\r\n\tat org.codehaus.groovy.runtime.callsite.AbstractCallSite.callCurrent(AbstractCallSite.java:203)\r\n\tat io.restassured.internal.RequestSpecificationImpl.get(RequestSpecificationImpl.groovy:171)\r\n\tat io.restassured.internal.RequestSpecificationImpl.get(RequestSpecificationImpl.groovy)\r\n\tat com.qa.stepDefs.ServicesStepDef.first_service_name_should_be(ServicesStepDef.java:33)\r\n\tat ✽.after user skipped 6 times, service id should be started from 7(file:///C:/Users/Naim/Desktop/IT/Projeler%20IntelliJ/bestBuyApi1/src/test/resources/features/services.feature:9)\r\n",
              "duration": 4095494400,
              "status": "failed"
            },
            "line": 9,
            "name": "after user skipped 6 times, service id should be started from 7",
            "match": {
              "arguments": [
                {
                  "val": "6",
                  "offset": 19
                },
                {
                  "val": "7",
                  "offset": 62
                }
              ],
              "location": "com.qa.stepDefs.ServicesStepDef.first_service_name_should_be(int,int)"
            },
            "keyword": "When "
          }
        ],
        "tags": [
          {
            "name": "@service"
          }
        ]
      },
      {
        "start_timestamp": "2021-10-12T09:16:33.887Z",
        "before": [
          {
            "result": {
              "status": "passed"
            },
            "match": {
              "location": "com.qa.stepDefs.Hook.setUp()"
            }
          }
        ],
        "line": 12,
        "name": "CRUD positive scenario of Services",
        "description": "",
        "id": "best-buy-services;crud-positive-scenario-of-services",
        "type": "scenario",
        "keyword": "Scenario",
        "steps": [
          {
            "result": {
              "error_message": "java.net.ConnectException: Connection refused: connect\r\n\tat java.base/sun.nio.ch.Net.connect0(Native Method)\r\n\tat java.base/sun.nio.ch.Net.connect(Net.java:503)\r\n\tat java.base/sun.nio.ch.Net.connect(Net.java:492)\r\n\tat java.base/sun.nio.ch.NioSocketImpl.connect(NioSocketImpl.java:588)\r\n\tat java.base/java.net.SocksSocketImpl.connect(SocksSocketImpl.java:333)\r\n\tat java.base/java.net.Socket.connect(Socket.java:648)\r\n\tat org.apache.http.conn.scheme.PlainSocketFactory.connectSocket(PlainSocketFactory.java:121)\r\n\tat org.apache.http.impl.conn.DefaultClientConnectionOperator.openConnection(DefaultClientConnectionOperator.java:180)\r\n\tat org.apache.http.impl.conn.ManagedClientConnectionImpl.open(ManagedClientConnectionImpl.java:326)\r\n\tat org.apache.http.impl.client.DefaultRequestDirector.tryConnect(DefaultRequestDirector.java:610)\r\n\tat org.apache.http.impl.client.DefaultRequestDirector.execute(DefaultRequestDirector.java:445)\r\n\tat org.apache.http.impl.client.AbstractHttpClient.doExecute(AbstractHttpClient.java:835)\r\n\tat org.apache.http.impl.client.CloseableHttpClient.execute(CloseableHttpClient.java:83)\r\n\tat org.apache.http.impl.client.CloseableHttpClient.execute(CloseableHttpClient.java:56)\r\n\tat org.apache.http.client.HttpClient$execute$0.call(Unknown Source)\r\n\tat org.codehaus.groovy.runtime.callsite.CallSiteArray.defaultCall(CallSiteArray.java:47)\r\n\tat org.apache.http.client.HttpClient$execute$0.call(Unknown Source)\r\n\tat io.restassured.internal.RequestSpecificationImpl$RestAssuredHttpBuilder.doRequest(RequestSpecificationImpl.groovy:2055)\r\n\tat io.restassured.internal.http.HTTPBuilder.post(HTTPBuilder.java:350)\r\n\tat io.restassured.internal.http.HTTPBuilder$post$3.call(Unknown Source)\r\n\tat org.codehaus.groovy.runtime.callsite.CallSiteArray.defaultCall(CallSiteArray.java:47)\r\n\tat org.codehaus.groovy.runtime.callsite.AbstractCallSite.call(AbstractCallSite.java:125)\r\n\tat org.codehaus.groovy.runtime.callsite.AbstractCallSite.call(AbstractCallSite.java:148)\r\n\tat io.restassured.internal.RequestSpecificationImpl.sendRequest(RequestSpecificationImpl.groovy:1181)\r\n\tat java.base/jdk.internal.reflect.NativeMethodAccessorImpl.invoke0(Native Method)\r\n\tat java.base/jdk.internal.reflect.NativeMethodAccessorImpl.invoke(NativeMethodAccessorImpl.java:62)\r\n\tat java.base/jdk.internal.reflect.DelegatingMethodAccessorImpl.invoke(DelegatingMethodAccessorImpl.java:43)\r\n\tat java.base/java.lang.reflect.Method.invoke(Method.java:564)\r\n\tat org.codehaus.groovy.reflection.CachedMethod.invoke(CachedMethod.java:107)\r\n\tat groovy.lang.MetaMethod.doMethodInvoke(MetaMethod.java:323)\r\n\tat groovy.lang.MetaClassImpl.invokeMethod(MetaClassImpl.java:1267)\r\n\tat groovy.lang.MetaClassImpl.invokeMethod(MetaClassImpl.java:1034)\r\n\tat groovy.lang.MetaClassImpl.invokeMethod(MetaClassImpl.java:818)\r\n\tat groovy.lang.GroovyObject.invokeMethod(GroovyObject.java:39)\r\n\tat org.codehaus.groovy.runtime.callsite.PogoInterceptableSite.call(PogoInterceptableSite.java:45)\r\n\tat org.codehaus.groovy.runtime.callsite.AbstractCallSite.call(AbstractCallSite.java:166)\r\n\tat io.restassured.internal.filter.SendRequestFilter.filter(SendRequestFilter.groovy:30)\r\n\tat io.restassured.filter.Filter$filter$0.call(Unknown Source)\r\n\tat org.codehaus.groovy.runtime.callsite.CallSiteArray.defaultCall(CallSiteArray.java:47)\r\n\tat io.restassured.filter.Filter$filter.call(Unknown Source)\r\n\tat io.restassured.internal.filter.FilterContextImpl.next(FilterContextImpl.groovy:72)\r\n\tat io.restassured.filter.time.TimingFilter.filter(TimingFilter.java:56)\r\n\tat io.restassured.filter.Filter$filter.call(Unknown Source)\r\n\tat org.codehaus.groovy.runtime.callsite.CallSiteArray.defaultCall(CallSiteArray.java:47)\r\n\tat io.restassured.filter.Filter$filter$0.call(Unknown Source)\r\n\tat io.restassured.internal.filter.FilterContextImpl.next(FilterContextImpl.groovy:72)\r\n\tat io.restassured.filter.FilterContext$next.call(Unknown Source)\r\n\tat io.restassured.internal.RequestSpecificationImpl.applyPathParamsAndSendRequest(RequestSpecificationImpl.groovy:1655)\r\n\tat java.base/jdk.internal.reflect.NativeMethodAccessorImpl.invoke0(Native Method)\r\n\tat java.base/jdk.internal.reflect.NativeMethodAccessorImpl.invoke(NativeMethodAccessorImpl.java:62)\r\n\tat java.base/jdk.internal.reflect.DelegatingMethodAccessorImpl.invoke(DelegatingMethodAccessorImpl.java:43)\r\n\tat java.base/java.lang.reflect.Method.invoke(Method.java:564)\r\n\tat org.codehaus.groovy.reflection.CachedMethod.invoke(CachedMethod.java:107)\r\n\tat groovy.lang.MetaMethod.doMethodInvoke(MetaMethod.java:323)\r\n\tat groovy.lang.MetaClassImpl.invokeMethod(MetaClassImpl.java:1267)\r\n\tat groovy.lang.MetaClassImpl.invokeMethod(MetaClassImpl.java:1034)\r\n\tat groovy.lang.MetaClassImpl.invokeMethod(MetaClassImpl.java:818)\r\n\tat groovy.lang.GroovyObject.invokeMethod(GroovyObject.java:39)\r\n\tat org.codehaus.groovy.runtime.callsite.PogoInterceptableSite.call(PogoInterceptableSite.java:45)\r\n\tat org.codehaus.groovy.runtime.callsite.PogoInterceptableSite.callCurrent(PogoInterceptableSite.java:55)\r\n\tat org.codehaus.groovy.runtime.callsite.AbstractCallSite.callCurrent(AbstractCallSite.java:203)\r\n\tat io.restassured.internal.RequestSpecificationImpl.applyPathParamsAndSendRequest(RequestSpecificationImpl.groovy:1661)\r\n\tat java.base/jdk.internal.reflect.NativeMethodAccessorImpl.invoke0(Native Method)\r\n\tat java.base/jdk.internal.reflect.NativeMethodAccessorImpl.invoke(NativeMethodAccessorImpl.java:62)\r\n\tat java.base/jdk.internal.reflect.DelegatingMethodAccessorImpl.invoke(DelegatingMethodAccessorImpl.java:43)\r\n\tat java.base/java.lang.reflect.Method.invoke(Method.java:564)\r\n\tat org.codehaus.groovy.reflection.CachedMethod.invoke(CachedMethod.java:107)\r\n\tat groovy.lang.MetaMethod.doMethodInvoke(MetaMethod.java:323)\r\n\tat groovy.lang.MetaClassImpl.invokeMethod(MetaClassImpl.java:1267)\r\n\tat groovy.lang.MetaClassImpl.invokeMethod(MetaClassImpl.java:1034)\r\n\tat groovy.lang.MetaClassImpl.invokeMethod(MetaClassImpl.java:818)\r\n\tat groovy.lang.GroovyObject.invokeMethod(GroovyObject.java:39)\r\n\tat org.codehaus.groovy.runtime.callsite.PogoInterceptableSite.call(PogoInterceptableSite.java:45)\r\n\tat org.codehaus.groovy.runtime.callsite.PogoInterceptableSite.callCurrent(PogoInterceptableSite.java:55)\r\n\tat org.codehaus.groovy.runtime.callsite.CallSiteArray.defaultCallCurrent(CallSiteArray.java:51)\r\n\tat org.codehaus.groovy.runtime.callsite.AbstractCallSite.callCurrent(AbstractCallSite.java:171)\r\n\tat org.codehaus.groovy.runtime.callsite.AbstractCallSite.callCurrent(AbstractCallSite.java:203)\r\n\tat io.restassured.internal.RequestSpecificationImpl.post(RequestSpecificationImpl.groovy:175)\r\n\tat io.restassured.internal.RequestSpecificationImpl.post(RequestSpecificationImpl.groovy)\r\n\tat com.qa.stepDefs.ServicesStepDef.user_creates_a_new_service_called(ServicesStepDef.java:46)\r\n\tat ✽.user creates a new service called \"Best Buy Germany\"(file:///C:/Users/Naim/Desktop/IT/Projeler%20IntelliJ/bestBuyApi1/src/test/resources/features/services.feature:13)\r\n",
              "duration": 4113392900,
              "status": "failed"
            },
            "line": 13,
            "name": "user creates a new service called \"Best Buy Germany\"",
            "match": {
              "arguments": [
                {
                  "val": "\"Best Buy Germany\"",
                  "offset": 34
                }
              ],
              "location": "com.qa.stepDefs.ServicesStepDef.user_creates_a_new_service_called(java.lang.String)"
            },
            "keyword": "When "
          },
          {
            "result": {
              "status": "skipped"
            },
            "line": 14,
            "name": "user updates a service with createdNewID and a new name \"Best Buy Italy\"",
            "match": {
              "arguments": [
                {
                  "val": "\"Best Buy Italy\"",
                  "offset": 56
                }
              ],
              "location": "com.qa.stepDefs.ServicesStepDef.user_is_able_to_update_a_service_called(java.lang.String)"
            },
            "keyword": "And "
          },
          {
            "result": {
              "duration": 1000300,
              "status": "skipped"
            },
            "line": 15,
            "name": "user is able to delete a service updated",
            "match": {
              "location": "com.qa.stepDefs.ServicesStepDef.user_is_able_to_delete_a_service_called()"
            },
            "keyword": "And "
          },
          {
            "result": {
              "duration": 998100,
              "status": "skipped"
            },
            "line": 16,
            "name": "user is able to see success message as \"Best Buy Italy\"",
            "match": {
              "arguments": [
                {
                  "val": "\"Best Buy Italy\"",
                  "offset": 39
                }
              ],
              "location": "com.qa.stepDefs.ServicesStepDef.user_is_able_to_see_success_message_as(java.lang.String)"
            },
            "keyword": "Then "
          }
        ],
        "tags": [
          {
            "name": "@service"
          },
          {
            "name": "@smoke"
          },
          {
            "name": "@regression"
          }
        ]
      },
      {
        "start_timestamp": "2021-10-12T09:16:38.020Z",
        "before": [
          {
            "result": {
              "status": "passed"
            },
            "match": {
              "location": "com.qa.stepDefs.Hook.setUp()"
            }
          }
        ],
        "line": 19,
        "name": "user is NOT able to see service with invalid ID - Negative Scenario",
        "description": "",
        "id": "best-buy-services;user-is-not-able-to-see-service-with-invalid-id---negative-scenario",
        "type": "scenario",
        "keyword": "Scenario",
        "steps": [
          {
            "result": {
              "error_message": "java.net.ConnectException: Connection refused: connect\r\n\tat java.base/sun.nio.ch.Net.connect0(Native Method)\r\n\tat java.base/sun.nio.ch.Net.connect(Net.java:503)\r\n\tat java.base/sun.nio.ch.Net.connect(Net.java:492)\r\n\tat java.base/sun.nio.ch.NioSocketImpl.connect(NioSocketImpl.java:588)\r\n\tat java.base/java.net.SocksSocketImpl.connect(SocksSocketImpl.java:333)\r\n\tat java.base/java.net.Socket.connect(Socket.java:648)\r\n\tat org.apache.http.conn.scheme.PlainSocketFactory.connectSocket(PlainSocketFactory.java:121)\r\n\tat org.apache.http.impl.conn.DefaultClientConnectionOperator.openConnection(DefaultClientConnectionOperator.java:180)\r\n\tat org.apache.http.impl.conn.ManagedClientConnectionImpl.open(ManagedClientConnectionImpl.java:326)\r\n\tat org.apache.http.impl.client.DefaultRequestDirector.tryConnect(DefaultRequestDirector.java:610)\r\n\tat org.apache.http.impl.client.DefaultRequestDirector.execute(DefaultRequestDirector.java:445)\r\n\tat org.apache.http.impl.client.AbstractHttpClient.doExecute(AbstractHttpClient.java:835)\r\n\tat org.apache.http.impl.client.CloseableHttpClient.execute(CloseableHttpClient.java:83)\r\n\tat org.apache.http.impl.client.CloseableHttpClient.execute(CloseableHttpClient.java:56)\r\n\tat org.apache.http.client.HttpClient$execute$0.call(Unknown Source)\r\n\tat org.codehaus.groovy.runtime.callsite.CallSiteArray.defaultCall(CallSiteArray.java:47)\r\n\tat org.apache.http.client.HttpClient$execute$0.call(Unknown Source)\r\n\tat io.restassured.internal.RequestSpecificationImpl$RestAssuredHttpBuilder.doRequest(RequestSpecificationImpl.groovy:2055)\r\n\tat io.restassured.internal.http.HTTPBuilder.doRequest(HTTPBuilder.java:495)\r\n\tat io.restassured.internal.http.HTTPBuilder.request(HTTPBuilder.java:452)\r\n\tat io.restassured.internal.http.HTTPBuilder$request$2.call(Unknown Source)\r\n\tat io.restassured.internal.RequestSpecificationImpl.sendHttpRequest(RequestSpecificationImpl.groovy:1451)\r\n\tat java.base/jdk.internal.reflect.NativeMethodAccessorImpl.invoke0(Native Method)\r\n\tat java.base/jdk.internal.reflect.NativeMethodAccessorImpl.invoke(NativeMethodAccessorImpl.java:62)\r\n\tat java.base/jdk.internal.reflect.DelegatingMethodAccessorImpl.invoke(DelegatingMethodAccessorImpl.java:43)\r\n\tat java.base/java.lang.reflect.Method.invoke(Method.java:564)\r\n\tat org.codehaus.groovy.reflection.CachedMethod.invoke(CachedMethod.java:107)\r\n\tat groovy.lang.MetaMethod.doMethodInvoke(MetaMethod.java:323)\r\n\tat groovy.lang.MetaClassImpl.invokeMethod(MetaClassImpl.java:1267)\r\n\tat groovy.lang.MetaClassImpl.invokeMethod(MetaClassImpl.java:1034)\r\n\tat groovy.lang.MetaClassImpl.invokeMethod(MetaClassImpl.java:818)\r\n\tat groovy.lang.GroovyObject.invokeMethod(GroovyObject.java:39)\r\n\tat org.codehaus.groovy.runtime.callsite.PogoInterceptableSite.call(PogoInterceptableSite.java:45)\r\n\tat org.codehaus.groovy.runtime.callsite.PogoInterceptableSite.callCurrent(PogoInterceptableSite.java:55)\r\n\tat io.restassured.internal.RequestSpecificationImpl.sendRequest(RequestSpecificationImpl.groovy:1200)\r\n\tat java.base/jdk.internal.reflect.NativeMethodAccessorImpl.invoke0(Native Method)\r\n\tat java.base/jdk.internal.reflect.NativeMethodAccessorImpl.invoke(NativeMethodAccessorImpl.java:62)\r\n\tat java.base/jdk.internal.reflect.DelegatingMethodAccessorImpl.invoke(DelegatingMethodAccessorImpl.java:43)\r\n\tat java.base/java.lang.reflect.Method.invoke(Method.java:564)\r\n\tat org.codehaus.groovy.reflection.CachedMethod.invoke(CachedMethod.java:107)\r\n\tat groovy.lang.MetaMethod.doMethodInvoke(MetaMethod.java:323)\r\n\tat groovy.lang.MetaClassImpl.invokeMethod(MetaClassImpl.java:1267)\r\n\tat groovy.lang.MetaClassImpl.invokeMethod(MetaClassImpl.java:1034)\r\n\tat groovy.lang.MetaClassImpl.invokeMethod(MetaClassImpl.java:818)\r\n\tat groovy.lang.GroovyObject.invokeMethod(GroovyObject.java:39)\r\n\tat org.codehaus.groovy.runtime.callsite.PogoInterceptableSite.call(PogoInterceptableSite.java:45)\r\n\tat org.codehaus.groovy.runtime.callsite.AbstractCallSite.call(AbstractCallSite.java:166)\r\n\tat io.restassured.internal.filter.SendRequestFilter.filter(SendRequestFilter.groovy:30)\r\n\tat io.restassured.filter.Filter$filter$0.call(Unknown Source)\r\n\tat org.codehaus.groovy.runtime.callsite.CallSiteArray.defaultCall(CallSiteArray.java:47)\r\n\tat io.restassured.filter.Filter$filter.call(Unknown Source)\r\n\tat io.restassured.internal.filter.FilterContextImpl.next(FilterContextImpl.groovy:72)\r\n\tat io.restassured.filter.time.TimingFilter.filter(TimingFilter.java:56)\r\n\tat io.restassured.filter.Filter$filter.call(Unknown Source)\r\n\tat org.codehaus.groovy.runtime.callsite.CallSiteArray.defaultCall(CallSiteArray.java:47)\r\n\tat io.restassured.filter.Filter$filter$0.call(Unknown Source)\r\n\tat io.restassured.internal.filter.FilterContextImpl.next(FilterContextImpl.groovy:72)\r\n\tat io.restassured.filter.FilterContext$next.call(Unknown Source)\r\n\tat io.restassured.internal.RequestSpecificationImpl.applyPathParamsAndSendRequest(RequestSpecificationImpl.groovy:1655)\r\n\tat java.base/jdk.internal.reflect.NativeMethodAccessorImpl.invoke0(Native Method)\r\n\tat java.base/jdk.internal.reflect.NativeMethodAccessorImpl.invoke(NativeMethodAccessorImpl.java:62)\r\n\tat java.base/jdk.internal.reflect.DelegatingMethodAccessorImpl.invoke(DelegatingMethodAccessorImpl.java:43)\r\n\tat java.base/java.lang.reflect.Method.invoke(Method.java:564)\r\n\tat org.codehaus.groovy.reflection.CachedMethod.invoke(CachedMethod.java:107)\r\n\tat groovy.lang.MetaMethod.doMethodInvoke(MetaMethod.java:323)\r\n\tat groovy.lang.MetaClassImpl.invokeMethod(MetaClassImpl.java:1267)\r\n\tat groovy.lang.MetaClassImpl.invokeMethod(MetaClassImpl.java:1034)\r\n\tat groovy.lang.MetaClassImpl.invokeMethod(MetaClassImpl.java:818)\r\n\tat groovy.lang.GroovyObject.invokeMethod(GroovyObject.java:39)\r\n\tat org.codehaus.groovy.runtime.callsite.PogoInterceptableSite.call(PogoInterceptableSite.java:45)\r\n\tat org.codehaus.groovy.runtime.callsite.PogoInterceptableSite.callCurrent(PogoInterceptableSite.java:55)\r\n\tat org.codehaus.groovy.runtime.callsite.AbstractCallSite.callCurrent(AbstractCallSite.java:203)\r\n\tat io.restassured.internal.RequestSpecificationImpl.applyPathParamsAndSendRequest(RequestSpecificationImpl.groovy:1661)\r\n\tat java.base/jdk.internal.reflect.NativeMethodAccessorImpl.invoke0(Native Method)\r\n\tat java.base/jdk.internal.reflect.NativeMethodAccessorImpl.invoke(NativeMethodAccessorImpl.java:62)\r\n\tat java.base/jdk.internal.reflect.DelegatingMethodAccessorImpl.invoke(DelegatingMethodAccessorImpl.java:43)\r\n\tat java.base/java.lang.reflect.Method.invoke(Method.java:564)\r\n\tat org.codehaus.groovy.reflection.CachedMethod.invoke(CachedMethod.java:107)\r\n\tat groovy.lang.MetaMethod.doMethodInvoke(MetaMethod.java:323)\r\n\tat groovy.lang.MetaClassImpl.invokeMethod(MetaClassImpl.java:1267)\r\n\tat groovy.lang.MetaClassImpl.invokeMethod(MetaClassImpl.java:1034)\r\n\tat groovy.lang.MetaClassImpl.invokeMethod(MetaClassImpl.java:818)\r\n\tat groovy.lang.GroovyObject.invokeMethod(GroovyObject.java:39)\r\n\tat org.codehaus.groovy.runtime.callsite.PogoInterceptableSite.call(PogoInterceptableSite.java:45)\r\n\tat org.codehaus.groovy.runtime.callsite.PogoInterceptableSite.callCurrent(PogoInterceptableSite.java:55)\r\n\tat org.codehaus.groovy.runtime.callsite.AbstractCallSite.callCurrent(AbstractCallSite.java:203)\r\n\tat io.restassured.internal.RequestSpecificationImpl.get(RequestSpecificationImpl.groovy:171)\r\n\tat io.restassured.internal.RequestSpecificationImpl.get(RequestSpecificationImpl.groovy)\r\n\tat com.qa.stepDefs.ServicesStepDef.user_sends_an_invalid_service_ID_x8(ServicesStepDef.java:88)\r\n\tat ✽.user sends an invalid service ID as \"x8\"(file:///C:/Users/Naim/Desktop/IT/Projeler%20IntelliJ/bestBuyApi1/src/test/resources/features/services.feature:20)\r\n",
              "duration": 4067888000,
              "status": "failed"
            },
            "line": 20,
            "name": "user sends an invalid service ID as \"x8\"",
            "match": {
              "arguments": [
                {
                  "val": "\"x8\"",
                  "offset": 36
                }
              ],
              "location": "com.qa.stepDefs.ServicesStepDef.user_sends_an_invalid_service_ID_x8(java.lang.String)"
            },
            "keyword": "When "
          },
          {
            "result": {
              "status": "skipped"
            },
            "line": 21,
            "name": "user is able to see error message as \"No record found for id \u0027x8\u0027\"",
            "match": {
              "arguments": [
                {
                  "val": "\"No record found for id \u0027x8\u0027\"",
                  "offset": 37
                }
              ],
              "location": "com.qa.stepDefs.ServicesStepDef.user_is_able_to_see_message(java.lang.String)"
            },
            "keyword": "Then "
          }
        ],
        "tags": [
          {
            "name": "@service"
          },
          {
            "name": "@regression"
          }
        ]
      },
      {
        "start_timestamp": "2021-10-12T09:16:42.105Z",
        "before": [
          {
            "result": {
              "status": "passed"
            },
            "match": {
              "location": "com.qa.stepDefs.Hook.setUp()"
            }
          }
        ],
        "line": 23,
        "name": "user is able to get service info with ID",
        "description": "",
        "id": "best-buy-services;user-is-able-to-get-service-info-with-id",
        "type": "scenario",
        "keyword": "Scenario",
        "steps": [
          {
            "result": {
              "error_message": "java.net.ConnectException: Connection refused: connect\r\n\tat java.base/sun.nio.ch.Net.connect0(Native Method)\r\n\tat java.base/sun.nio.ch.Net.connect(Net.java:503)\r\n\tat java.base/sun.nio.ch.Net.connect(Net.java:492)\r\n\tat java.base/sun.nio.ch.NioSocketImpl.connect(NioSocketImpl.java:588)\r\n\tat java.base/java.net.SocksSocketImpl.connect(SocksSocketImpl.java:333)\r\n\tat java.base/java.net.Socket.connect(Socket.java:648)\r\n\tat org.apache.http.conn.scheme.PlainSocketFactory.connectSocket(PlainSocketFactory.java:121)\r\n\tat org.apache.http.impl.conn.DefaultClientConnectionOperator.openConnection(DefaultClientConnectionOperator.java:180)\r\n\tat org.apache.http.impl.conn.ManagedClientConnectionImpl.open(ManagedClientConnectionImpl.java:326)\r\n\tat org.apache.http.impl.client.DefaultRequestDirector.tryConnect(DefaultRequestDirector.java:610)\r\n\tat org.apache.http.impl.client.DefaultRequestDirector.execute(DefaultRequestDirector.java:445)\r\n\tat org.apache.http.impl.client.AbstractHttpClient.doExecute(AbstractHttpClient.java:835)\r\n\tat org.apache.http.impl.client.CloseableHttpClient.execute(CloseableHttpClient.java:83)\r\n\tat org.apache.http.impl.client.CloseableHttpClient.execute(CloseableHttpClient.java:56)\r\n\tat org.apache.http.client.HttpClient$execute$0.call(Unknown Source)\r\n\tat io.restassured.internal.RequestSpecificationImpl$RestAssuredHttpBuilder.doRequest(RequestSpecificationImpl.groovy:2055)\r\n\tat io.restassured.internal.http.HTTPBuilder.doRequest(HTTPBuilder.java:495)\r\n\tat io.restassured.internal.http.HTTPBuilder.request(HTTPBuilder.java:452)\r\n\tat io.restassured.internal.http.HTTPBuilder$request$2.call(Unknown Source)\r\n\tat io.restassured.internal.RequestSpecificationImpl.sendHttpRequest(RequestSpecificationImpl.groovy:1451)\r\n\tat java.base/jdk.internal.reflect.NativeMethodAccessorImpl.invoke0(Native Method)\r\n\tat java.base/jdk.internal.reflect.NativeMethodAccessorImpl.invoke(NativeMethodAccessorImpl.java:62)\r\n\tat java.base/jdk.internal.reflect.DelegatingMethodAccessorImpl.invoke(DelegatingMethodAccessorImpl.java:43)\r\n\tat java.base/java.lang.reflect.Method.invoke(Method.java:564)\r\n\tat org.codehaus.groovy.reflection.CachedMethod.invoke(CachedMethod.java:107)\r\n\tat groovy.lang.MetaMethod.doMethodInvoke(MetaMethod.java:323)\r\n\tat groovy.lang.MetaClassImpl.invokeMethod(MetaClassImpl.java:1267)\r\n\tat groovy.lang.MetaClassImpl.invokeMethod(MetaClassImpl.java:1034)\r\n\tat groovy.lang.MetaClassImpl.invokeMethod(MetaClassImpl.java:818)\r\n\tat groovy.lang.GroovyObject.invokeMethod(GroovyObject.java:39)\r\n\tat org.codehaus.groovy.runtime.callsite.PogoInterceptableSite.call(PogoInterceptableSite.java:45)\r\n\tat org.codehaus.groovy.runtime.callsite.PogoInterceptableSite.callCurrent(PogoInterceptableSite.java:55)\r\n\tat io.restassured.internal.RequestSpecificationImpl.sendRequest(RequestSpecificationImpl.groovy:1200)\r\n\tat java.base/jdk.internal.reflect.NativeMethodAccessorImpl.invoke0(Native Method)\r\n\tat java.base/jdk.internal.reflect.NativeMethodAccessorImpl.invoke(NativeMethodAccessorImpl.java:62)\r\n\tat java.base/jdk.internal.reflect.DelegatingMethodAccessorImpl.invoke(DelegatingMethodAccessorImpl.java:43)\r\n\tat java.base/java.lang.reflect.Method.invoke(Method.java:564)\r\n\tat org.codehaus.groovy.reflection.CachedMethod.invoke(CachedMethod.java:107)\r\n\tat groovy.lang.MetaMethod.doMethodInvoke(MetaMethod.java:323)\r\n\tat groovy.lang.MetaClassImpl.invokeMethod(MetaClassImpl.java:1267)\r\n\tat groovy.lang.MetaClassImpl.invokeMethod(MetaClassImpl.java:1034)\r\n\tat groovy.lang.MetaClassImpl.invokeMethod(MetaClassImpl.java:818)\r\n\tat groovy.lang.GroovyObject.invokeMethod(GroovyObject.java:39)\r\n\tat org.codehaus.groovy.runtime.callsite.PogoInterceptableSite.call(PogoInterceptableSite.java:45)\r\n\tat org.codehaus.groovy.runtime.callsite.AbstractCallSite.call(AbstractCallSite.java:166)\r\n\tat io.restassured.internal.filter.SendRequestFilter.filter(SendRequestFilter.groovy:30)\r\n\tat io.restassured.filter.Filter$filter$0.call(Unknown Source)\r\n\tat org.codehaus.groovy.runtime.callsite.CallSiteArray.defaultCall(CallSiteArray.java:47)\r\n\tat io.restassured.filter.Filter$filter.call(Unknown Source)\r\n\tat io.restassured.internal.filter.FilterContextImpl.next(FilterContextImpl.groovy:72)\r\n\tat io.restassured.filter.time.TimingFilter.filter(TimingFilter.java:56)\r\n\tat io.restassured.filter.Filter$filter.call(Unknown Source)\r\n\tat org.codehaus.groovy.runtime.callsite.CallSiteArray.defaultCall(CallSiteArray.java:47)\r\n\tat io.restassured.filter.Filter$filter$0.call(Unknown Source)\r\n\tat io.restassured.internal.filter.FilterContextImpl.next(FilterContextImpl.groovy:72)\r\n\tat io.restassured.filter.FilterContext$next.call(Unknown Source)\r\n\tat io.restassured.internal.RequestSpecificationImpl.applyPathParamsAndSendRequest(RequestSpecificationImpl.groovy:1655)\r\n\tat java.base/jdk.internal.reflect.NativeMethodAccessorImpl.invoke0(Native Method)\r\n\tat java.base/jdk.internal.reflect.NativeMethodAccessorImpl.invoke(NativeMethodAccessorImpl.java:62)\r\n\tat java.base/jdk.internal.reflect.DelegatingMethodAccessorImpl.invoke(DelegatingMethodAccessorImpl.java:43)\r\n\tat java.base/java.lang.reflect.Method.invoke(Method.java:564)\r\n\tat org.codehaus.groovy.reflection.CachedMethod.invoke(CachedMethod.java:107)\r\n\tat groovy.lang.MetaMethod.doMethodInvoke(MetaMethod.java:323)\r\n\tat groovy.lang.MetaClassImpl.invokeMethod(MetaClassImpl.java:1267)\r\n\tat groovy.lang.MetaClassImpl.invokeMethod(MetaClassImpl.java:1034)\r\n\tat groovy.lang.MetaClassImpl.invokeMethod(MetaClassImpl.java:818)\r\n\tat groovy.lang.GroovyObject.invokeMethod(GroovyObject.java:39)\r\n\tat org.codehaus.groovy.runtime.callsite.PogoInterceptableSite.call(PogoInterceptableSite.java:45)\r\n\tat org.codehaus.groovy.runtime.callsite.PogoInterceptableSite.callCurrent(PogoInterceptableSite.java:55)\r\n\tat org.codehaus.groovy.runtime.callsite.AbstractCallSite.callCurrent(AbstractCallSite.java:203)\r\n\tat io.restassured.internal.RequestSpecificationImpl.applyPathParamsAndSendRequest(RequestSpecificationImpl.groovy:1661)\r\n\tat java.base/jdk.internal.reflect.NativeMethodAccessorImpl.invoke0(Native Method)\r\n\tat java.base/jdk.internal.reflect.NativeMethodAccessorImpl.invoke(NativeMethodAccessorImpl.java:62)\r\n\tat java.base/jdk.internal.reflect.DelegatingMethodAccessorImpl.invoke(DelegatingMethodAccessorImpl.java:43)\r\n\tat java.base/java.lang.reflect.Method.invoke(Method.java:564)\r\n\tat org.codehaus.groovy.reflection.CachedMethod.invoke(CachedMethod.java:107)\r\n\tat groovy.lang.MetaMethod.doMethodInvoke(MetaMethod.java:323)\r\n\tat groovy.lang.MetaClassImpl.invokeMethod(MetaClassImpl.java:1267)\r\n\tat groovy.lang.MetaClassImpl.invokeMethod(MetaClassImpl.java:1034)\r\n\tat groovy.lang.MetaClassImpl.invokeMethod(MetaClassImpl.java:818)\r\n\tat groovy.lang.GroovyObject.invokeMethod(GroovyObject.java:39)\r\n\tat org.codehaus.groovy.runtime.callsite.PogoInterceptableSite.call(PogoInterceptableSite.java:45)\r\n\tat org.codehaus.groovy.runtime.callsite.PogoInterceptableSite.callCurrent(PogoInterceptableSite.java:55)\r\n\tat org.codehaus.groovy.runtime.callsite.AbstractCallSite.callCurrent(AbstractCallSite.java:203)\r\n\tat io.restassured.internal.RequestSpecificationImpl.get(RequestSpecificationImpl.groovy:171)\r\n\tat io.restassured.internal.RequestSpecificationImpl.get(RequestSpecificationImpl.groovy)\r\n\tat com.qa.stepDefs.ServicesStepDef.user_sends_a_GET_request_with_ID(ServicesStepDef.java:104)\r\n\tat ✽.user sends a GET request with 5(file:///C:/Users/Naim/Desktop/IT/Projeler%20IntelliJ/bestBuyApi1/src/test/resources/features/services.feature:24)\r\n",
              "duration": 4030218300,
              "status": "failed"
            },
            "line": 24,
            "name": "user sends a GET request with 5",
            "match": {
              "arguments": [
                {
                  "val": "5",
                  "offset": 30
                }
              ],
              "location": "com.qa.stepDefs.ServicesStepDef.user_sends_a_GET_request_with_ID(int)"
            },
            "keyword": "When "
          },
          {
            "result": {
              "status": "skipped"
            },
            "line": 25,
            "name": "user is able to see requested service 5",
            "match": {
              "arguments": [
                {
                  "val": "5",
                  "offset": 38
                }
              ],
              "location": "com.qa.stepDefs.ServicesStepDef.user_is_able_to_see_requested_service(int)"
            },
            "keyword": "Then "
          }
        ],
        "tags": [
          {
            "name": "@service"
          }
        ]
      }
    ],
    "name": "Best Buy Services",
    "description": "",
    "id": "best-buy-services",
    "keyword": "Feature",
    "uri": "file:src/test/resources/features/services.feature",
    "tags": [
      {
        "name": "@service",
        "type": "Tag",
        "location": {
          "line": 1,
          "column": 1
        }
      }
    ]
  }
]